pynteractor/__init__.py
pynteractor/context.py
pynteractor/errors.py
pynteractor/interactor.py
pynteractor/organizer.py
pynteractor-0.2.dist-info/METADATA
pynteractor-0.2.dist-info/RECORD
pynteractor-0.2.dist-info/WHEEL
pynteractor-0.2.dist-info/top_level.txt
