Metadata-Version: 2.1
Name: pynteractor
Version: 0.2
Summary: Lib to ease business logic separation
Home-page: https://github.com/mota/pynteractor
Author: Pierre Wacrenier
Author-email: pierre@wacrenier.me
License: ISC
Platform: UNKNOWN
